setup.py
great_justice/__init__.py
great_justice/structure.py
great_justice/utils.py
great_justice.egg-info/PKG-INFO
great_justice.egg-info/SOURCES.txt
great_justice.egg-info/dependency_links.txt
great_justice.egg-info/requires.txt
great_justice.egg-info/top_level.txt
great_justice.egg-info/zip-safe